owl_client/__init__.py
owl_client/cli.py
owl_client/schema.py
owl_client/utils.py
owl_client/scripts/__init__.py
owl_client/scripts/logs_pipeline.py
owl_client/scripts/run_standalone.py
owl_pipeline_client-0.10.0.dist-info/AUTHORS.rst
owl_pipeline_client-0.10.0.dist-info/LICENSE
owl_pipeline_client-0.10.0.dist-info/METADATA
owl_pipeline_client-0.10.0.dist-info/WHEEL
owl_pipeline_client-0.10.0.dist-info/entry_points.txt
owl_pipeline_client-0.10.0.dist-info/top_level.txt
owl_pipeline_client-0.10.0.dist-info/RECORD
